LICENSE
MANIFEST.in
README.md
requirements.txt
setup.py
astrobox/__init__.py
astrobox/cargo.py
astrobox/core.py
astrobox/guns.py
astrobox/space_field.py
astrobox/theme.py
astrobox/utils.py
astrobox.egg-info/PKG-INFO
astrobox.egg-info/SOURCES.txt
astrobox.egg-info/dependency_links.txt
astrobox.egg-info/requires.txt
astrobox.egg-info/top_level.txt
astrobox/themes/__init__.py
astrobox/themes/default/__init__.py
astrobox/themes/default/background.png
astrobox/themes/default/mothership_1_crashed.png
astrobox/themes/default/mothership_2_crashed.png
astrobox/themes/default/mothership_3_crashed.png
astrobox/themes/default/mothership_4_crashed.png
astrobox/themes/default/not-found.png
astrobox/themes/default/asteroids/1.png
astrobox/themes/default/asteroids/2.png
astrobox/themes/default/asteroids/3.png
astrobox/themes/default/asteroids/4.png
astrobox/themes/default/asteroids/5.png
astrobox/themes/default/asteroids/6.png
astrobox/themes/default/asteroids/7.png
astrobox/themes/default/asteroids/8.png
astrobox/themes/default/asteroids/9.png
astrobox/themes/default/motherships/any_mothership_explosion.png
astrobox/themes/default/motherships/1/blow_up_1.png
astrobox/themes/default/motherships/1/blow_up_2.png
astrobox/themes/default/motherships/1/crashed.png
astrobox/themes/default/motherships/2/blow_up_1.png
astrobox/themes/default/motherships/2/blow_up_2.png
astrobox/themes/default/motherships/2/crashed.png
astrobox/themes/default/motherships/3/blow_up_1.png
astrobox/themes/default/motherships/3/blow_up_2.png
astrobox/themes/default/motherships/3/crashed.png
astrobox/themes/default/motherships/4/blow_up_1.png
astrobox/themes/default/motherships/4/blow_up_2.png
astrobox/themes/default/motherships/4/crashed.png
astrobox/themes/default/teams/any_drone_explosion.png
astrobox/themes/default/teams/any_projectile_explosion.png
astrobox/themes/default/teams/1/blow_up_1.png
astrobox/themes/default/teams/1/blow_up_2.png
astrobox/themes/default/teams/1/blow_up_3.png
astrobox/themes/default/teams/1/drone.png
astrobox/themes/default/teams/1/drone_crashed.png
astrobox/themes/default/teams/1/mothership.png
