Metadata-Version: 2.1
Name: astrobox
Version: 1.5.0
Summary: The package allows you to create Astro Robo Game for programmers.
Home-page: https://github.com/suguby/astrobox
Author: Shandrinov Vadim
Author-email: suguby@gmail.com
License: BSD License
Platform: UNKNOWN
Classifier: Development Status :: 4 - Beta
Classifier: License :: OSI Approved :: BSD License
Classifier: Programming Language :: Python
Classifier: Programming Language :: Python :: 3.6
Classifier: Programming Language :: Python :: 3.7
Classifier: Programming Language :: Python :: 3.8
